endrpi/__init__.py
endrpi/cli.py
endrpi/server.py
endrpi/_public/app.css
endrpi/_public/app.js
endrpi/_public/index.html
endrpi/_public/swagger-ui/LICENSE
endrpi/_public/swagger-ui/swagger-ui-bundle.js
endrpi/_public/swagger-ui/swagger-ui.css
endrpi/actions/__init__.py
endrpi/actions/pin.py
endrpi/actions/system.py
endrpi/config/__init__.py
endrpi/config/logging.py
endrpi/config/pin_factory.py
endrpi/model/__init__.py
endrpi/model/action_result.py
endrpi/model/frequency.py
endrpi/model/measurement.py
endrpi/model/memory.py
endrpi/model/message.py
endrpi/model/pin.py
endrpi/model/platform.py
endrpi/model/system.py
endrpi/model/temperature.py
endrpi/model/throttle.py
endrpi/model/up_time.py
endrpi/model/websocket.py
endrpi/routes/__init__.py
endrpi/routes/pin.py
endrpi/routes/system.py
endrpi/routes/websocket.py
endrpi/utils/__init__.py
endrpi/utils/api.py
endrpi/utils/bitwise.py
endrpi/utils/process.py
endrpi-1.0.0b22.dist-info/LICENSE
endrpi-1.0.0b22.dist-info/METADATA
endrpi-1.0.0b22.dist-info/WHEEL
endrpi-1.0.0b22.dist-info/entry_points.txt
endrpi-1.0.0b22.dist-info/top_level.txt
endrpi-1.0.0b22.dist-info/RECORD
