Metadata-Version: 2.1
Name: endrpi
Version: 1.0.0b22
Summary: Endpoints for Raspberry Pi (Endrpi) is a web API server for the Raspberry Pi that provides basic statuses and GPIO controls through a collection of HTTP endpoints.
Home-page: https://endrpi.io
Author: Persanix LLC
Author-email: opensource@persanix.com
License: UNKNOWN
Project-URL: Documentation, https://endrpi.io
Project-URL: Source, https://github.com/persanix-llc/endrpi-server
Project-URL: Bug Tracker, https://github.com/persanix-llc/endrpi-server/issues
Platform: UNKNOWN
Classifier: Programming Language :: Python :: 3
Classifier: License :: OSI Approved :: Apache Software License
Classifier: Operating System :: OS Independent
Requires-Python: >=3.7
License-File: LICENSE
Requires-Dist: fastapi (==0.68.1)
Requires-Dist: uvicorn (==0.15.0)
Requires-Dist: pydantic (==1.8.2)
Requires-Dist: aiofiles (==0.7.0)
Requires-Dist: gpiozero (==1.6.2)
Requires-Dist: loguru (==0.5.3)
